test_project/__init__.py
test_project/runtests.py
test_project/settings.py
test_project/urls.py
ydcommon/__init__.py
ydcommon/fab.py
ydcommon/models.py
ydcommon/settings.py
ydcommon/views.py
ydcommon/management/__init__.py
ydcommon/management/commands/__init__.py
ydcommon/management/commands/check_migrations.py
ydcommon/management/commands/check_test_requirements.py
ydcommon/management/commands/clear_database.py
ydcommon/management/commands/dump_database.py
ydcommon/management/commands/jshint.py
ydcommon/management/commands/run_qunit.py
ydcommon/scripts/run-qunit.js
ydcommon/tests/__init__.py
ydcommon/tests/test_check_test_requirements.py
ydcommon/tests/test_jshint.py
ydcommon/tests/test_qunit.py
ydcommon/tests/test_utils.py
ydcommon/utils/__init__.py
ydcommon/utils/settings.py
ydcommon/utils/urls.py
ydcommon-0.1.68.dist-info/DESCRIPTION.rst
ydcommon-0.1.68.dist-info/METADATA
ydcommon-0.1.68.dist-info/RECORD
ydcommon-0.1.68.dist-info/WHEEL
ydcommon-0.1.68.dist-info/metadata.json
ydcommon-0.1.68.dist-info/top_level.txt
