Metadata-Version: 2.0
Name: ydcommon
Version: 0.1.68
Summary: YD Technology common libraries
Home-page: https://github.com/ArabellaTech/ydcommon
Author: Arabella
Author-email: team@arabel.la
License: MIT
Platform: UNKNOWN
Classifier: License :: OSI Approved :: MIT License
Classifier: Intended Audience :: Developers
Classifier: Operating System :: OS Independent
Classifier: Programming Language :: Python
Classifier: Programming Language :: Python :: 2.7
Classifier: Programming Language :: Python :: 3.4
Classifier: Programming Language :: Python :: 3.5
Classifier: Programming Language :: Python :: 3.6
Requires-Dist: Fabric3 (>=1.11.1.post1)
Requires-Dist: pycrypto (>=2.6.1)
